{
  "@context": {
    "ldp": "http://www.w3.org/ns/ldp#",
    "schema": "http://schema.org/",
    "fedora": "http://fedora.info/definitions/v4/repository#",
    "webac": "http://fedora.info/definitions/v4/webac#",
    "acl": "http://www.w3.org/ns/auth/acl#",
    "ucdlib": "http://digital.ucdavis.edu/schema#",
    "ebucore": "http://www.ebu.ch/metadata/ontologies/ebucore/ebucore#"
  },
  "@id": "",
  "@type": [
    "schema:VisualArtwork",
    "schema:ImageObject",
    "schema:CreativeWork",
    "http://fedora.info/definitions/v4/repository#ArchivalGroup"
  ],
  "schema:City": "Walla Walla",
  "schema:State": "Washington",
  "schema:about": [
    {
      "@id": "http://id.worldcat.org/fast/1212424"
    },
    {
      "@id": "http://id.worldcat.org/fast/1802520"
    },
    {
      "@id": "http://id.worldcat.org/fast/1208940"
    }
  ],
  "schema:associatedMedia": {
    "@id": "@base:/D211_45_39.tif"
  },
  "schema:creator": "Mojonnier & Sons, Inc.",
  "schema:identifier": [
    "D-211, Box:45, Folder:39",
    "ark:/87293/d39c6s44j"
  ],
  "schema:keywords": "Pears",
  "schema:license": {
    "@id": "http://rightsstatements.org/vocab/InC-NC/1.0/"
  },
  "schema:location": "Walla Walla, Walla Walla Co., Washington",
  "schema:name": "Blue Mountain",
  "schema:publisher": "UC Davis Library, Archives and Special Collections",
  "https://www.wikidata.org/wiki/Q28575": "Walla Walla Co."
}